UE_SSD1306/__init__.py
UE_SSD1306/ssd1306.py
UE_SSD1306-0.1.dist-info/LICENSE
UE_SSD1306-0.1.dist-info/METADATA
UE_SSD1306-0.1.dist-info/WHEEL
UE_SSD1306-0.1.dist-info/top_level.txt
UE_SSD1306-0.1.dist-info/RECORD
