Metadata-Version: 2.1
Name: UE-SSD1306
Version: 0.1
Summary: i2c ssd1306 display driver for micropython
Author: Master
Author-email: cesar.bautista@uelectronics.com
License: MIT
License-File: LICENSE
